cardimpose/__init__.py
cardimpose/__main__.py
cardimpose/cardimpose.py
cardimpose/layout.py
cardimpose/parse.py
cardimpose-0.2.2.dist-info/licenses/LICENSE.md
tests/__init__.py
tests/test_impose.py
tests/test_layout.py
tests/test_parser.py
cardimpose-0.2.2.dist-info/METADATA
cardimpose-0.2.2.dist-info/WHEEL
cardimpose-0.2.2.dist-info/entry_points.txt
cardimpose-0.2.2.dist-info/top_level.txt
cardimpose-0.2.2.dist-info/RECORD
