Metadata-Version: 2.4
Name: cardimpose
Version: 0.2.2
Summary: Impose multiple copies of a pdf onto a larger document.
Home-page: https://github.com/frsche/cardimpose
Author: Frederik Scheerer
Keywords: imposition,print,pdf
License-File: LICENSE.md
Requires-Dist: pymupdf
Dynamic: author
Dynamic: description
Dynamic: description-content-type
Dynamic: home-page
Dynamic: keywords
Dynamic: license-file
Dynamic: requires-dist
Dynamic: summary
